consolidate/__init__.py
consolidate/consolidatemodule.py
consolidatepy-0.0.7.dist-info/METADATA
consolidatepy-0.0.7.dist-info/WHEEL
consolidatepy-0.0.7.dist-info/top_level.txt
consolidatepy-0.0.7.dist-info/RECORD
